aliendev_sentiment/__init__.py
aliendev_sentiment/main.py
aliendev_sentiment-0.1.7.dist-info/LICENSE
aliendev_sentiment-0.1.7.dist-info/METADATA
aliendev_sentiment-0.1.7.dist-info/WHEEL
aliendev_sentiment-0.1.7.dist-info/RECORD
