Metadata-Version: 2.1
Name: aliendev-sentiment
Version: 0.1.7
Summary: 
Home-page: https://github.com/masnasri-a
License: MIT
Author: Nasri Adzlani
Author-email: nasriadzlani@live.com
Requires-Python: >=3.10,<4.0
Classifier: License :: OSI Approved :: MIT License
Classifier: Programming Language :: Python :: 3
Classifier: Programming Language :: Python :: 3.10
Classifier: Programming Language :: Python :: 3.11
Requires-Dist: deep-translator (>=1.11.4,<2.0.0)
Requires-Dist: vadersentiment (>=3.3.2,<4.0.0)
Project-URL: Repository, https://github.com/masnasri-a/aliendev-sentiment
